pkgu.py
tests/__init__.py
tests/test_pkgu.py
pkgu-0.0.28.dist-info/LICENSE
pkgu-0.0.28.dist-info/METADATA
pkgu-0.0.28.dist-info/WHEEL
pkgu-0.0.28.dist-info/entry_points.txt
pkgu-0.0.28.dist-info/top_level.txt
pkgu-0.0.28.dist-info/RECORD
