Metadata-Version: 2.1
Name: pkgu
Version: 0.0.28
Summary: Manage the installed package by providing support for updating and uninstalling.
Home-page: https://github.com/Abeautifulsnow/pkgu
Author: Abeautifulsnow <lnrunstone.0727@gmail.com>
Author-email: lcprunstone@163.com
License: MIT
Keywords: python3,pip,pip install pkg --upgrade,pip-update,uninstall
Classifier: Development Status :: 4 - Beta
Classifier: Environment :: Console
Classifier: Intended Audience :: Developers
Classifier: License :: OSI Approved :: MIT License
Classifier: Operating System :: OS Independent
Classifier: Programming Language :: Python
Classifier: Programming Language :: Python :: 3.10
Classifier: Programming Language :: Python :: 3.11
Classifier: Topic :: Software Development :: Libraries
License-File: LICENSE
Requires-Dist: pydantic (>=1.10.5)
Requires-Dist: orjson (>=3.8.10)
Requires-Dist: prettytable (>=3.8.0)
Requires-Dist: loguru (>=0.6.0)
Requires-Dist: colorama (>=0.4.5)
Requires-Dist: halo (>=0.0.31)
Requires-Dist: toml (>=0.10.2)
Requires-Dist: py-retry (>=0.0.4)
Requires-Dist: simple-term-menu (>=1.5.0)
Requires-Dist: inquirer (>=3.1.3)
